h9nt/__init__.py
h9nt-1.0.1.dist-info/METADATA
h9nt-1.0.1.dist-info/WHEEL
h9nt-1.0.1.dist-info/top_level.txt
h9nt-1.0.1.dist-info/RECORD
