Metadata-Version: 2.1
Name: h9nt
Version: 1.0.1
Summary: A Simple Algorithm utils with protobuf in python
Author: vardxg
Author-email: <vardxgdev@gmail.com>
Keywords: python,dev,free,algo
Classifier: Development Status :: 1 - Planning
Classifier: Intended Audience :: Developers
Classifier: Programming Language :: Python :: 3
Classifier: Operating System :: Unix
Classifier: Operating System :: MacOS :: MacOS X
Classifier: Operating System :: Microsoft :: Windows
